<?xml version = '1.0' encoding = 'UTF-8'?>
<Entity class="oracle.dbtools.crest.model.design.logical.Entity" id="FD84E63E-2A38-804F-8E84-306987FA1214" directorySegmentName="seg_0" name="ACTOR">
<createdBy>maddene</createdBy>
<createdTime>2013-03-06 20:52:18 UTC</createdTime>
<ownerDesignName>GroupProjectModel</ownerDesignName>
<engineerTo>
<item key="3A91A740-A85E-12AD-3B48-15135405E3D4" value="true"/>
</engineerTo>
<pkName>SECONDARY ARTIST PK</pkName>
<adequatelyNormalized>NO</adequatelyNormalized>
<expectedVolumes>0</expectedVolumes>
<fwdEngineeringStrategyName>Single Table</fwdEngineeringStrategyName>
<growthPercent>0</growthPercent>
<growthType>Year</growthType>
<maxVolumes>9999999</maxVolumes>
<minVolumes>0</minVolumes>
<normalForm>Third</normalForm>
<fonts>
<FontObject class="oracle.dbtools.crest.model.design.FontObjectWr">
<foType>Title</foType>
<fontStyle>1</fontStyle>
<colorRGB>-16776961</colorRGB>
</FontObject>
<FontObject class="oracle.dbtools.crest.model.design.FontObjectWr">
<foType>Attribute</foType>
<colorRGB>-16777216</colorRGB>
</FontObject>
<FontObject class="oracle.dbtools.crest.model.design.FontObjectWr">
<foType>Datatype</foType>
<colorRGB>-16744448</colorRGB>
</FontObject>
<FontObject class="oracle.dbtools.crest.model.design.FontObjectWr">
<foType>PK Element</foType>
<colorRGB>-16776961</colorRGB>
</FontObject>
<FontObject class="oracle.dbtools.crest.model.design.FontObjectWr">
<foType>FK Element</foType>
<colorRGB>-16777216</colorRGB>
</FontObject>
<FontObject class="oracle.dbtools.crest.model.design.FontObjectWr">
<foType>UK Element</foType>
<colorRGB>-16776961</colorRGB>
</FontObject>
<FontObject class="oracle.dbtools.crest.model.design.FontObjectWr">
<foType>Not Null</foType>
<colorRGB>-65536</colorRGB>
</FontObject>
<FontObject class="oracle.dbtools.crest.model.design.FontObjectWr">
<foType>Key</foType>
<colorRGB>-16777216</colorRGB>
</FontObject>
</fonts>
<attributes>
<Attribute class="oracle.dbtools.crest.model.design.logical.Attribute" name="Actor_ID" id="004EE87F-D9C6-9E92-DA09-7686D1AAA229">
<createdBy>maddene</createdBy>
<createdTime>2013-03-06 20:52:18 UTC</createdTime>
<ownerDesignName>GroupProjectModel</ownerDesignName>
<engineerTo>
<item key="3A91A740-A85E-12AD-3B48-15135405E3D4" value="true"/>
</engineerTo>
<use>0</use>
</Attribute>
<Attribute class="oracle.dbtools.crest.model.design.logical.Attribute" name="Actor_Name" id="B57FF4BE-564D-2620-62CA-31C8A87E3669">
<createdBy>maddene</createdBy>
<createdTime>2013-03-06 20:52:18 UTC</createdTime>
<ownerDesignName>GroupProjectModel</ownerDesignName>
<engineerTo>
<item key="3A91A740-A85E-12AD-3B48-15135405E3D4" value="true"/>
</engineerTo>
<nullsAllowed>true</nullsAllowed>
<use>0</use>
</Attribute>
<Attribute class="oracle.dbtools.crest.model.design.logical.Attribute" name="Movie_ID" id="46D92907-3A48-6C3E-5C3D-EFDAC0054432">
<createdBy>maddene</createdBy>
<createdTime>2013-03-06 20:53:17 UTC</createdTime>
<generatorID>8049E311-1C08-324D-2E7F-94515D9A7D6A</generatorID>
<ownerDesignName>GroupProjectModel</ownerDesignName>
<engineerTo>
<item key="3A91A740-A85E-12AD-3B48-15135405E3D4" value="true"/>
</engineerTo>
<referedAttribute>9ADBEDE4-7AB1-B320-CFBE-529DEE7156A4</referedAttribute>
<use>0</use>
</Attribute>
</attributes>
<identifiers>
<identifier class="oracle.dbtools.crest.model.design.logical.CandidateKey" id="A992CE9A-2F59-61F8-E183-C5A3FAA4D452" name="ACTOR PK">
<createdBy>maddene</createdBy>
<createdTime>2013-03-06 20:52:18 UTC</createdTime>
<ownerDesignName>GroupProjectModel</ownerDesignName>
<engineerTo>
<item key="3A91A740-A85E-12AD-3B48-15135405E3D4" value="true"/>
</engineerTo>
<pk>true</pk>
<usedAttributes>
<attributeRef>004EE87F-D9C6-9E92-DA09-7686D1AAA229</attributeRef>
<attributeRef>46D92907-3A48-6C3E-5C3D-EFDAC0054432</attributeRef>
</usedAttributes>
</identifier>
</identifiers>
</Entity>